README.md
setup.cfg
setup.py
login/__init__.py
login/login.py
loginForPython.egg-info/PKG-INFO
loginForPython.egg-info/SOURCES.txt
loginForPython.egg-info/dependency_links.txt
loginForPython.egg-info/requires.txt
loginForPython.egg-info/top_level.txt