Metadata-Version: 2.1
Name: loginForPython
Version: 0.1
Summary: Pre-Alpha of simple login system
Home-page: https://github.com/Matthias-coding/updater/
Author: Matthias
Author-email: matthias.harzer03@gmail.com
License: MIT
Download-URL: https://github.com/Matthias-coding/loginForPython/archive/v_0.1.tar.gz
Keywords: Firebase,Pyrebase,Updater
Platform: UNKNOWN
Classifier: Development Status :: 3 - Alpha
Classifier: Intended Audience :: Developers
Classifier: Topic :: Software Development :: Build Tools
Classifier: License :: OSI Approved :: MIT License
Classifier: Programming Language :: Python :: 3.7
